postpanda_helper/__init__.py
postpanda_helper/_geo_helpers.py
postpanda_helper/geo_helpers.py
postpanda_helper/normalizer.py
postpanda_helper/pandas_reader.py
postpanda_helper/pandas_writer.py
postpanda_helper/pd_helpers.py
postpanda_helper/psql_helpers.py
postpanda_helper/py.typed
postpanda_helper/select_sert.py
postpanda_helper-1.2.1.dist-info/LICENSE
postpanda_helper-1.2.1.dist-info/WHEEL
postpanda_helper-1.2.1.dist-info/METADATA
postpanda_helper-1.2.1.dist-info/RECORD
